asynccontextstack/__init__.py
asynccontextstack-1.0.0.dist-info/LICENSE
asynccontextstack-1.0.0.dist-info/METADATA
asynccontextstack-1.0.0.dist-info/WHEEL
asynccontextstack-1.0.0.dist-info/entry_points.txt
asynccontextstack-1.0.0.dist-info/RECORD
